{
  "slug": "acupuncture-for-acid-reflux-gerd",
  "image": "https://images.unsplash.com/photo-1512621776951-a57141f2eefd?auto=format&fit=crop&w=1200&q=80",
  "title": "Acid Reflux and TCM: What a More Individualized Treatment Plan May Involve",
  "author": "Dr. Huang Clinic Editorial Team",
  "status": "scheduled",
  "excerpt": "Reflux is not always just about food triggers. This article explains how stress, meal timing, body tension, and digestive patterns can all shape symptoms—and where acupuncture may fit into supportive care.",
  "category": "digestive",
  "featured": false,
  "imageAlt": "Healthy meal on a table representing gentle digestive support",
  "publishAt": "2026-10-05T13:00:00.000Z",
  "imageCredit": "Photo by Brooke Lark on Unsplash",
  "imageSource": "https://unsplash.com/photos/08bOYnH_r_E",
  "publishDate": "2026-10-06",
  "contentMarkdown": "# Acid Reflux and TCM: What a More Individualized Treatment Plan May Involve\n\nPeople often talk about acid reflux as if it is only about eating the wrong foods. Food matters, but many patients notice something more complicated: reflux gets worse during stressful periods, after late meals, with poor sleep, or when the whole digestive system feels irritated and unpredictable.\n\nThat is one reason some patients look into acupuncture or Chinese medicine. They are not only asking how to quiet symptoms for one night. They want to understand why the pattern keeps coming back.\n\n---\n\n## Reflux often has more than one trigger\n\nCommon contributors include:\n\n- eating too late\n- large meals eaten quickly\n- stress and tension\n- poor sleep\n- coffee, alcohol, or highly irritating foods\n- a digestive system that already feels sensitive\n\nFor some people, reflux mainly feels like burning. For others, it is throat irritation, chest discomfort, sour taste, or coughing after meals. That variation matters.\n\n---\n\n## Where acupuncture may fit\n\nAcupuncture may help as supportive care by:\n\n- calming stress-related flare patterns\n- easing upper abdominal or chest tension\n- supporting smoother digestive regulation\n- helping related symptoms such as poor sleep or bloating\n\nThis is usually not a one-visit fix. It is better understood as part of a broader plan, especially when symptoms are recurring.\n\n---\n\n## Why an individualized approach matters\n\nTwo patients can both say “I have reflux” but mean very different things. One may worsen with stress and tightness. Another may worsen mostly with late eating. Another may also have bloating, irregular stools, or fatigue.\n\nThat is why Chinese medicine often asks wider questions about sleep, stress, appetite, and digestion rather than treating reflux as one isolated symptom.\n\nIf your symptoms overlap with broader digestive disruption, you may also want to review our [IBS and digestive issues](/en/conditions#ibs) page or [Chinese herbal medicine](/en/services#chinese-herbal-medicine) service.\n\n---\n\n## When to get medical evaluation first\n\nSupportive care has limits. It is important to get medical evaluation if you have:\n\n- trouble swallowing\n- unexplained weight loss\n- vomiting\n- black stools or GI bleeding concerns\n- persistent chest pain that is not clearly digestive\n\nAcupuncture can be part of care, but serious or changing symptoms still need proper medical assessment.\n\n---\n\n## FAQ\n\n### Can acupuncture cure reflux?\nIt is better to think of it as supportive care that may help symptom patterns and regulation, not a guaranteed cure.\n\n### Is reflux always caused by food?\nNo. Food matters, but stress, sleep, and meal timing often play a major role too.\n\n### Can I use acupuncture with regular medical care?\nYes. Many patients use it alongside primary care or GI care.\n\n---\n\n## Final thought\n\nIf reflux has become a pattern rather than an occasional annoyance, it usually helps to stop treating it as only a food problem. An individualized plan often makes more sense than reacting one symptom at a time.\n\nIf you are in Middletown or nearby and want to talk through your symptoms, you can [book a consultation](/en/contact).",
  "relatedServices": [
    "acupuncture",
    "chinese-herbal-medicine",
    "lifestyle-counseling"
  ],
  "translationGroup": "acupuncture-for-acid-reflux-gerd",
  "relatedConditions": [
    "acid-reflux",
    "ibs",
    "stress"
  ]
}